tron/__init__.py
tron/cli.py
tron/devtron_api.py
tron/utils.py
tron/validators.py
tron/version.py
tron/core/__init__.py
tron/core/app/__init__.py
tron/core/app/base_configurations/__init__.py
tron/core/app/base_configurations/baseConfiguration.py
tron/core/app/base_configurations/baseConfigurationApproval.py
tron/core/app/base_configurations/baseDeploymentTemplate.py
tron/core/app/base_configurations/configMapSecret.py
tron/core/app/base_configurations/configMapSecretApproval.py
tron/core/app/build_config/__init__.py
tron/core/app/build_config/createBuildConfig.py
tron/core/app/build_config/updateBuildConfig.py
tron/core/app/env_override_configurations/__init__.py
tron/core/app/env_override_configurations/envConfigMapSecret.py
tron/core/app/env_override_configurations/env_override_handler.py
tron/core/app/env_override_configurations/overrideDeploymentTemplate.py
tron/core/app/git_material/__init__.py
tron/core/app/git_material/githandler.py
tron/core/app/git_material/update_githandler.py
tron/core/app/metadata/__init__.py
tron/core/app/metadata/saveMetadata.py
tron/core/app/workflow/__init__.py
tron/core/app/workflow/workflow_handler.py
tron/core/app/workflow/cd_pipeline/__init__.py
tron/core/app/workflow/cd_pipeline/cd_pipeline_handler.py
tron/core/app/workflow/cd_pipeline/cd_pipeline_models.py
tron/core/app/workflow/ci_pipeline/__init__.py
tron/core/app/workflow/ci_pipeline/ci_pipeline_handler.py
tron/core/app/workflow/ci_pipeline/ci_pipeline_models.py
tron/util/__init__.py
tron/util/exception_handlers.py
devtron_cli-0.2.7.dist-info/METADATA
devtron_cli-0.2.7.dist-info/WHEEL
devtron_cli-0.2.7.dist-info/entry_points.txt
devtron_cli-0.2.7.dist-info/top_level.txt
devtron_cli-0.2.7.dist-info/RECORD
