Metadata-Version: 2.4
Name: devtron-cli
Version: 0.2.7
Summary: Automated infrastructure and application management tool for Devtron
Home-page: https://github.com/devtron-labs/tron-cli
Author: Devtron Devops
Author-email: devops@devtron.ai
Classifier: Programming Language :: Python :: 3
Classifier: License :: OSI Approved :: MIT License
Classifier: Operating System :: OS Independent
Requires-Python: >=3.7
Requires-Dist: PyYAML>=6.0
Requires-Dist: requests>=2.28.0
Requires-Dist: click>=8.0.0
Requires-Dist: jsonmerge>=1.9.2
Requires-Dist: deepdiff>=6.0.0
Dynamic: author
Dynamic: author-email
Dynamic: classifier
Dynamic: description
Dynamic: description-content-type
Dynamic: home-page
Dynamic: requires-dist
Dynamic: requires-python
Dynamic: summary
